APIShift/__init__.py
APIShift/conversation.py
APIShift/exceptions.py
APIShift/providers.py
apishift-1.0.1.dist-info/licenses/LICENSE
apishift-1.0.1.dist-info/METADATA
apishift-1.0.1.dist-info/WHEEL
apishift-1.0.1.dist-info/top_level.txt
apishift-1.0.1.dist-info/RECORD
