Metadata-Version: 2.4
Name: APIShift
Version: 1.0.1
Summary: A package for managing multiple LLM providers with automatic key shifting to bypass rate limits and quotas while maintaining conversation context.
Author-email: Aditya190803 <aditya.mer@somaiya.edu>
License: MIT License
Project-URL: Homepage, https://github.com/Aditya190803/APIShift
Project-URL: Repository, https://github.com/Aditya190803/APIShift
Requires-Python: >=3.11
License-File: LICENSE
Requires-Dist: groq
Requires-Dist: google-generativeai
Requires-Dist: requests
Requires-Dist: faiss-cpu
Requires-Dist: sentence-transformers
Dynamic: license-file
